README.md
setup.cfg
setup.py
recapuccino/__init__.py
recapuccino.egg-info/PKG-INFO
recapuccino.egg-info/SOURCES.txt
recapuccino.egg-info/dependency_links.txt
recapuccino.egg-info/requires.txt
recapuccino.egg-info/top_level.txt
recapuccino/xvalidation/__init__.py